nabs/__init__.py
nabs/_version.py
nabs/callbacks.py
nabs/exceptions.py
nabs/optimize.py
nabs/plan_stubs.py
nabs/plans.py
nabs/preprocessors.py
nabs/simulators.py
nabs/streams.py
nabs/utils.py
nabs/version.py
nabs/visualizations.py
nabs/tests/__init__.py
nabs/tests/conftest.py
nabs/tests/test_callbacks.py
nabs/tests/test_optimize.py
nabs/tests/test_plan_stubs.py
nabs/tests/test_plans.py
nabs/tests/test_preprocessors.py
nabs/tests/test_simulators.py
nabs/tests/test_streams.py
nabs-1.5.7.dist-info/licenses/AUTHORS.rst
nabs-1.5.7.dist-info/licenses/LICENSE.md
nabs-1.5.7.dist-info/METADATA
nabs-1.5.7.dist-info/WHEEL
nabs-1.5.7.dist-info/top_level.txt
nabs-1.5.7.dist-info/RECORD
