Metadata-Version: 2.4
Name: nabs
Version: 1.5.7
Summary: NABS: Not a beamline scientist. Beamline automatation that should be handled by code, not by people.
Author: SLAC National Accelerator Laboratory
License: Copyright (c) 2023, The Board of Trustees of the Leland Stanford Junior
Classifier: Development Status :: 5 - Production/Stable
Classifier: Natural Language :: English
Classifier: Programming Language :: Python :: 3
Requires-Python: >=3.9
License-File: LICENSE.md
License-File: AUTHORS.rst
Requires-Dist: bluesky
Requires-Dist: numpy
Requires-Dist: ophyd
Requires-Dist: pandas
Requires-Dist: scipy
Requires-Dist: toolz
Provides-Extra: test
Requires-Dist: flake8; extra == "test"
Requires-Dist: matplotlib; extra == "test"
Requires-Dist: pyqt5; extra == "test"
Requires-Dist: pytest; extra == "test"
Requires-Dist: pytest-timeout; extra == "test"
Requires-Dist: pcdsdaq; extra == "test"
Requires-Dist: pcdsdevices; extra == "test"
Provides-Extra: doc
Requires-Dist: sphinx; extra == "doc"
Requires-Dist: sphinx_rtd_theme; extra == "doc"
Requires-Dist: sphinxcontrib-jquery; extra == "doc"
Dynamic: license-file
